Metadata-Version: 2.1
Name: django-simple-json-api
Version: 0.0.3
Summary: Create simple JSON APIs with Django
Home-page: https://github.com/francescozoccheddu/Django-Simple-JSON-API
Author: Francesco Zoccheddu
License: MIT
Platform: UNKNOWN
Classifier: License :: OSI Approved :: MIT License
Classifier: Programming Language :: Python :: 3
Classifier: Programming Language :: Python :: 3.7
